modulemaster.py
modulemaster-0.1.0.dist-info/METADATA
modulemaster-0.1.0.dist-info/WHEEL
modulemaster-0.1.0.dist-info/top_level.txt
modulemaster-0.1.0.dist-info/RECORD
